[{"reference":"Genesis 4:15","eng_before":["“Not so!”","replied","the LORD.","“If anyone","slays","Cain,"],"eng_word":"[then Cain] will be avenged","eng_after":["sevenfold.”","And the LORD","placed","a mark","on Cain,","so that no one","who found him","would kill","him."],"og_before":["לָכֵן֙","וַיֹּ֧אמֶר","יְהוָ֗ה","כָּל־","הֹרֵ֣ג","קַ֔יִן"],"og_word":"יֻקָּ֑ם","og_after":["שִׁבְעָתַ֖יִם","יְהוָ֤ה","וַיָּ֨שֶׂם","א֔וֹת","לְקַ֙יִן֙","לְבִלְתִּ֥י","מֹצְאֽוֹ׃","הַכּוֹת־","אֹת֖וֹ"]},{"reference":"Genesis 4:24","eng_before":["If","Cain"],"eng_word":"is avenged","eng_after":["sevenfold,","then Lamech","seventy-sevenfold.”"],"og_before":["כִּ֥י","קָ֑יִן"],"og_word":"יֻקַּם־","og_after":["שִׁבְעָתַ֖יִם","וְלֶ֖מֶךְ","וְשִׁבְעָֽה׃"]},{"reference":"Exodus 21:20","eng_before":["If","a man","strikes","his male","or","female servant","with a rod,","and the servant dies","by","his hand,"],"eng_word":"be punished.","eng_after":[],"og_before":["וְכִֽי־","אִ֨ישׁ","יַכֶּה֩","עַבְדּ֜וֹ","א֤וֹ","אֲמָתוֹ֙","בַּשֵּׁ֔בֶט","וּמֵ֖ת","תַּ֣חַת","יָד֑וֹ"],"og_word":"יִנָּקֵֽם׃","og_after":[]},{"reference":"Exodus 21:20","eng_before":["If","a man","strikes","his male","or","female servant","with a rod,","and the servant dies","by","his hand,","he shall surely","be punished."],"eng_after":[],"og_before":["וְכִֽי־","אִ֨ישׁ","יַכֶּה֩","עַבְדּ֜וֹ","א֤וֹ","אֲמָתוֹ֙","בַּשֵּׁ֔בֶט","וּמֵ֖ת","תַּ֣חַת","יָד֑וֹ","נָקֹ֖ם","יִנָּקֵֽם׃"],"og_after":[]},{"reference":"Exodus 21:21","eng_before":["However,","if","the slave gets up","after a day","or","two,","the owner shall not"],"eng_word":"be punished,","eng_after":["since","[the slave is]","his property."],"og_before":["אַ֥ךְ","אִם־","יַעֲמֹ֑ד","י֛וֹם","א֥וֹ","יוֹמַ֖יִם","לֹ֣א"],"og_word":"יֻקַּ֔ם","og_after":["כִּ֥י","הֽוּא׃","כַסְפּ֖וֹ"]},{"reference":"Leviticus 19:18","eng_before":["Do not"],"eng_word":"seek revenge","eng_after":["or bear a grudge","against any","of your people,","but love","your neighbor","as yourself.","I","am the LORD."],"og_before":["לֹֽא־"],"og_word":"תִקֹּ֤ם","og_after":["תִטֹּר֙","בְּנֵ֣י","עַמֶּ֔ךָ","וְאָֽהַבְתָּ֥","לְרֵעֲךָ֖","כָּמ֑וֹךָ","אֲנִ֖י","יְהוָֽה׃"]},{"reference":"Leviticus 26:25","eng_before":["And I will bring","a sword","against you"],"eng_word":"to execute","eng_after":["the vengeance","of the covenant.","Though you withdraw","into","your cities,","I will send","a pestilence","among you,","and you will be delivered","into the hand","of the enemy."],"og_before":["וְהֵבֵאתִ֨י","חֶ֗רֶב","עֲלֵיכֶ֜ם"],"og_word":"נֹקֶ֙מֶת֙","og_after":["נְקַם־","בְּרִ֔ית","וְנֶאֱסַפְתֶּ֖ם","אֶל־","עָרֵיכֶ֑ם","וְשִׁלַּ֤חְתִּי","דֶ֙בֶר֙","בְּת֣וֹכְכֶ֔ם","וְנִתַּתֶּ֖ם","בְּיַד־","אוֹיֵֽב׃"]},{"reference":"Numbers 31:2","eng_before":[],"eng_word":"“Take vengeance","eng_after":["on","the Midianites","for the Israelites.","After that,","you will be gathered","to","your people.”"],"og_before":[],"og_word":"נְקֹ֗ם","og_after":["מֵאֵ֖ת","הַמִּדְיָנִ֑ים","בְּנֵ֣י","אַחַ֖ר","תֵּאָסֵ֥ף","אֶל־","עַמֶּֽיךָ׃"]},{"reference":"Deuteronomy 32:43","eng_before":["Rejoice, [O heavens, with Him, and let all God’s angels worship Him.]הַרְנִ֤ינוּ (har·nî·nū)Verb - Hifil - Imperative - masculine pluralStrong's 7442:  To give a ringing cry[Rejoice,] O Gentiles,גוֹיִם֙ (ḡō·w·yim)Noun - masculine pluralStrong's 1471:  A foreign nation, a Gentile, a troop of animals, a flight of locusts[with] His people;עַמּ֔וֹ (‘am·mōw)Noun - masculine singular construct | third person masculine singularStrong's 5971:  A people, a tribe, troops, attendants, a flockforכִּ֥י (kî)ConjunctionStrong's 3588:  A relative conjunctionHe will avengeיִקּ֑וֹם (yiq·qō·wm)Verb - Qal - Imperfect - third person masculine singularStrong's 5358:  To grudge, avenge, punishthe bloodדַם־ (ḏam-)Noun - masculine singular constructStrong's 1818:  Blood, of man, an animal, the juice of the grape, bloodshedof His children.עֲבָדָ֖יו (‘ă·ḇā·ḏāw)Noun - masculine plural construct | third person masculine singularStrong's 5650:  Slave, servantHe will takeיָשִׁ֣יב (yā·šîḇ)Verb - Hifil - Imperfect - third person masculine singularStrong's 7725:  To turn back, in, to retreat, againvengeanceוְנָקָם֙ (wə·nā·qām)Conjunctive waw | Noun - masculine singularStrong's 5359:  Vengeanceon His adversaries [and repay those who hate Him];לְצָרָ֔יו (lə·ṣā·rāw)Preposition-l | Noun - masculine plural construct | third person masculine singularStrong's 6862:  Narrow, a tight place, a pebble, an opponentHe will cleanseוְכִפֶּ֥ר (wə·ḵip·per)Conjunctive waw | Verb - Piel - Conjunctive perfect - third person masculine singularStrong's 3722:  To cover, to expiate, condone, to placate, cancelHis landאַדְמָת֖וֹ (’aḏ·mā·ṯōw)Noun - feminine singular construct | third person masculine singularStrong's 127:  Ground, land[and] His people.”עַמּֽוֹ׃ (‘am·mōw)Noun - masculine singular construct | third person masculine singularStrong's 5971:  A people, a tribe, troops, attendants, a flockJump to PreviousAdversaries Aloud Atone Avenge Avenges Avengeth Blood Enemies Expiation Haters Joy Makes Maketh Merciful Nations Pardoned Payment Praise Punishment Rejoice Render Rendereth Servants Shout Sin Sing Turneth VengeanceJump to NextAdversaries Aloud Atone Avenge Avenges Avengeth Blood Enemies Expiation Haters Joy Makes Maketh Merciful Nations Pardoned Payment Praise Punishment Rejoice Render Rendereth Servants Shout Sin Sing Turneth VengeanceLinksDeuteronomy 32:43 NIVDeuteronomy 32:43 NLTDeuteronomy 32:43 ESVDeuteronomy 32:43 NASBDeuteronomy 32:43 KJVDeuteronomy 32:43  BibleApps.comDeuteronomy 32:43 Biblia ParalelaDeuteronomy 32:43 Chinese BibleDeuteronomy 32:43 French BibleDeuteronomy 32:43 Clyx QuotationsOT Law: Deuteronomy 32:43 Rejoice you nations with his people (Deut. De Du)","[Rejoice,] O Gentiles,","[with] His people;","for"],"eng_word":"He will avenge","eng_after":["the blood","of His children.","He will take","vengeance","on His adversaries","He will cleanse","His land","[and] His people.”"],"og_before":["הַרְנִ֤ינוּ","גוֹיִם֙","עַמּ֔וֹ","כִּ֥י"],"og_word":"יִקּ֑וֹם","og_after":["דַם־","עֲבָדָ֖יו","יָשִׁ֣יב","וְנָקָם֙","לְצָרָ֔יו","וְכִפֶּ֥ר","אַדְמָת֖וֹ","עַמּֽוֹ׃"]},{"reference":"Joshua 10:13","eng_before":["So the sun","stood still","and the moon","stopped","until","the nation"],"eng_word":"took vengeance","eng_after":["upon its enemies.","Is this","not","written","in","the Book","of Jashar?","“So the sun","stopped","in the middle","of the sky","and delayed","going down","almost a full","day.?"],"og_before":["הַשֶּׁ֜מֶשׁ","וַיִּדֹּ֨ם","וְיָרֵ֣חַ","עָמָ֗ד","עַד־","גּוֹי֙"],"og_word":"יִקֹּ֥ם","og_after":["אֹֽיְבָ֔יו","הִ֥יא","הֲלֹא־","כְתוּבָ֖ה","עַל־","סֵ֣פֶר","הַיָּשָׁ֑ר","הַשֶּׁ֙מֶשׁ֙","וַיַּעֲמֹ֤ד","בַּחֲצִ֣י","הַשָּׁמַ֔יִם","וְלֹא־","לָב֖וֹא","תָּמִֽים׃","כְּי֥וֹם"]},{"reference":"Judges 15:7","eng_before":["And Samson","told them,","“Because","you have done","this,","I will not rest","until"],"eng_word":"I have taken vengeance","eng_after":["upon you.”"],"og_before":["שִׁמְשׁ֔וֹן","וַיֹּ֤אמֶר","אִֽם־","תַּעֲשׂ֖וּן","כָּזֹ֑את","אֶחְדָּֽל׃","כִּ֛י"],"og_word":"נִקַּ֥מְתִּי","og_after":["בָכֶ֖ם"]},{"reference":"Judges 16:28","eng_before":["Then Samson","called out","to","the LORD:","“O Lord","GOD,","please","remember me.","Strengthen me,","O God,","just","once more,","so that with one","vengeful blow"],"eng_word":"I may pay back","eng_after":["the Philistines","for my two","eyes.”"],"og_before":["שִׁמְשׁ֛וֹן","וַיִּקְרָ֥א","אֶל־","יֱהֹוִ֡ה","אֲדֹנָ֣י","יְהוָ֖ה","נָא֩","זָכְרֵ֣נִי","וְחַזְּקֵ֨נִי","הָאֱלֹהִ֔ים","אַ֣ךְ","הַפַּ֤עַם","אַחַ֛ת","נְקַם־"],"og_word":"וְאִנָּקְמָ֧ה","og_after":["מִפְּלִשְׁתִּֽים׃","מִשְּׁתֵ֥י","עֵינַ֖י"]},{"reference":"1 Samuel 14:24","eng_before":["Now the men","of Israel","were in distress","that","day,","for Saul","had placed the troops","under an oath,","saying,","“Cursed [is]","the man","who","eats","[any] food","before","evening,"],"eng_word":"before I have taken vengeance","eng_after":["on my enemies.”","So none","of the troops","tasted","any food."],"og_before":["וְאִֽישׁ־","יִשְׂרָאֵ֥ל","נִגַּ֖שׂ","הַה֑וּא","בַּיּ֣וֹם","שָׁא֨וּל","הָעָ֜ם","וַיֹּאֶל֩","לֵאמֹ֗ר","אָר֣וּר","הָ֠אִישׁ","אֲשֶׁר־","יֹ֨אכַל","לֶ֜חֶם","עַד־","הָעֶ֗רֶב"],"og_word":"וְנִקַּמְתִּי֙","og_after":["מֵאֹ֣יְבַ֔י","וְלֹֽא","הָעָ֖ם","טָעַ֥ם","לָֽחֶם׃"]},{"reference":"1 Samuel 18:25","eng_before":["Saul","replied,","“Say","to David,","‘The king","desires","no","other dowry","but","a hundred","Philistine","foreskins"],"eng_word":"as revenge","eng_after":["on his","enemies.’”","But Saul","intended","to cause David’s","death","at the hands","of the Philistines."],"og_before":["שָׁא֜וּל","וַיֹּ֨אמֶר","תֹאמְר֣וּ","לְדָוִ֗ד","לַמֶּ֙לֶךְ֙","חֵ֤פֶץ","אֵֽין־","בְּמֹ֔הַר","כִּ֗י","בְּמֵאָה֙","פְּלִשְׁתִּ֔ים","עָרְל֣וֹת"],"og_word":"לְהִנָּקֵ֖ם","og_after":["הַמֶּ֑לֶךְ","בְּאֹיְבֵ֣י","וְשָׁא֣וּל","חָשַׁ֔ב","דָּוִ֖ד","לְהַפִּ֥יל","בְּיַד־","פְּלִשְׁתִּֽים׃"]},{"reference":"1 Samuel 24:12","eng_before":["May the LORD","judge","between you and me,","and may the LORD"],"eng_word":"take vengeance","eng_after":["on you,","but my hand","will never","be","against you."],"og_before":["יְהוָה֙","יִשְׁפֹּ֤ט","בֵּינִ֣י","יְהוָ֖ה"],"og_word":"וּנְקָמַ֥נִי","og_after":["מִמֶּ֑ךָּ","וְיָדִ֖י","לֹ֥א","תִֽהְיֶה־","בָּֽךְ׃"]},{"reference":"2 Kings 9:7","eng_before":["And you are to strike down","the house","of your master","Ahab,"],"eng_word":"so that I may avenge","eng_after":["the blood","of My servants","the prophets","[and]","all","the servants","of the LORD","[shed] by the hand","of Jezebel."],"og_before":["וְהִ֨כִּיתָ֔ה","בֵּ֥ית","אֲדֹנֶ֑יךָ","אַחְאָ֖ב"],"og_word":"וְנִקַּמְתִּ֞י","og_after":["דְּמֵ֣י ׀","עֲבָדַ֣י","הַנְּבִיאִ֗ים","וּדְמֵ֛י","כָּל־","עַבְדֵ֥י","יְהוָ֖ה","מִיַּ֥ד","אִיזָֽבֶל׃"]},{"reference":"Esther 8:13","eng_before":["A copy","of the text,","issued","as law","throughout every","province,","was distributed","to all","the peoples,","so that the Jews","would be","prepared","on that","day"],"eng_word":"to avenge themselves","eng_after":["on their enemies."],"og_before":["פַּתְשֶׁ֣גֶן","הַכְּתָ֗ב","לְהִנָּ֤תֵֽן","דָּת֙","בְּכָל־","מְדִינָ֣ה","גָּל֖וּי","לְכָל־","הָעַמִּ֑ים","הַיְּהוּדִ֤ים","וְלִהְי֨וֹת","עֲתִידִים֙","הַזֶּ֔ה","לַיּ֣וֹם"],"og_word":"לְהִנָּקֵ֖ם","og_after":["מֵאֹיְבֵיהֶֽם׃"]},{"reference":"Psalm 8:2","eng_before":["From the lips","of children","and infants","You have ordained","praise","on account of","Your adversaries,","to silence","the enemy"],"eng_word":"and avenger.","eng_after":[],"og_before":["מִפִּ֤י","עֽוֹלְלִ֨ים ׀","וְֽיֹנְקִים֮","יִסַּ֪דְתָּ֫","עֹ֥ז","לְמַ֥עַן","צוֹרְרֶ֑יךָ","לְהַשְׁבִּ֥ית","א֝וֹיֵ֗ב"],"og_word":"וּמִתְנַקֵּֽם׃","og_after":[]},{"reference":"Psalm 44:16","eng_before":["at the voice","of the scorner","and reviler,","because of","the enemy,"],"eng_word":"bent on revenge.","eng_after":[],"og_before":["מִ֭קּוֹל","מְחָרֵ֣ף","וּמְגַדֵּ֑ף","מִפְּנֵ֥י","א֝וֹיֵ֗ב"],"og_word":"וּמִתְנַקֵּֽם׃","og_after":[]},{"reference":"Psalm 99:8","eng_before":["O LORD","our God,","You","answered them.","You were","a forgiving","God","to them,"],"eng_word":"yet an avenger","eng_after":["of","their misdeeds."],"og_before":["יְהוָ֣ה","אֱלֹהֵינוּ֮","אַתָּ֪ה","עֲנִ֫יתָ֥ם","הָיִ֣יתָ","נֹ֭שֵׂא","אֵ֣ל","לָהֶ֑ם"],"og_word":"וְ֝נֹקֵ֗ם","og_after":["עַל־","עֲלִילוֹתָֽם׃"]},{"reference":"Isaiah 1:24","eng_before":["Therefore","the Lord","GOD","of Hosts,","the Mighty","One of Israel,","declares:","“Ah,","I will be relieved","of My foes"],"eng_word":"and avenge Myself","eng_after":["on My enemies."],"og_before":["לָכֵ֗ן","הָֽאָדוֹן֙","יְהוָ֣ה","צְבָא֔וֹת","אֲבִ֖יר","יִשְׂרָאֵ֑ל","נְאֻ֤ם","ה֚וֹי","אֶנָּחֵ֣ם","מִצָּרַ֔י"],"og_word":"וְאִנָּקְמָ֖ה","og_after":["מֵאוֹיְבָֽי׃"]},{"reference":"Jeremiah 5:9","eng_before":["Should I not","punish","them for","these things?”","declares","the LORD.","“Should I not"],"eng_word":"avenge","eng_after":["Myself","on such a nation","as this?"],"og_before":["לוֹא־","אֶפְקֹ֖ד","הַֽעַל־","אֵ֥לֶּה","נְאֻם־","יְהֹוָ֑ה","לֹ֥א"],"og_word":"תִתְנַקֵּ֖ם","og_after":["נַפְשִֽׁי׃","בְּג֣וֹי","כָּזֶ֔ה"]},{"reference":"Jeremiah 5:29","eng_before":["Should I not","punish","them for","these things?","declares","the LORD.","Should I not"],"eng_word":"avenge","eng_after":["Myself","on such a nation","as this?"],"og_before":["לֹֽא־","אֶפְקֹ֖ד","הַֽעַל־","אֵ֥לֶּה","נְאֻם־","יְהֹוָ֑ה","לֹ֥א"],"og_word":"תִתְנַקֵּ֖ם","og_after":["נַפְשִֽׁי׃","בְּג֣וֹי","כָּזֶ֔ה"]},{"reference":"Jeremiah 9:9","eng_before":["Should I not","punish them","for","these things?","declares","the LORD.","Should I not"],"eng_word":"avenge","eng_after":["Myself","on","such a nation","as this?”"],"og_before":["לֹֽא־","אֶפְקָד־","הַעַל־","אֵ֥לֶּה","נְאֻם־","יְהוָ֑ה","לֹ֥א"],"og_word":"תִתְנַקֵּ֖ם","og_after":["נַפְשִֽׁי׃","אִ֚ם","בְּג֣וֹי","כָּזֶ֔ה"]},{"reference":"Jeremiah 15:15","eng_before":["You","understand,","O LORD;","remember me","and attend to me."],"eng_word":"Avenge me","eng_after":["against","my persecutors.","In Your patience,","do not","take me away.","Know that","I endure","reproach","for Your honor."],"og_before":["אַתָּ֧ה","יָדַ֣עְתָּ","יְהוָ֗ה","זָכְרֵ֤נִי","וּפָקְדֵ֙נִי֙"],"og_word":"וְהִנָּ֤קֶם","og_after":["לִי֙","מֵרֹ֣דְפַ֔י","לְאֶ֥רֶךְ","אַל־","תִּקָּחֵ֑נִי","דַּ֕ע","שְׂאֵתִ֥י","חֶרְפָּֽה׃","עָלֶ֖יךָ"]},{"reference":"Jeremiah 46:10","eng_before":["That","day","belongs to the Lord,","the GOD","of Hosts,","a day","of vengeance"],"eng_word":"to avenge Himself","eng_after":["against His foes.","The sword","will devour","until it is satisfied,","until it is quenched","with their blood.","For","it will be a sacrifice","to the Lord,","the GOD","of Hosts,","in the land","of the north","by","the River","Euphrates."],"og_before":["הַה֜וּא","וְֽהַיּ֨וֹם","לַאדֹנָ֧י","יְהוִ֣ה","צְבָא֗וֹת","י֤וֹם","נְקָמָה֙"],"og_word":"לְהִנָּקֵ֣ם","og_after":["מִצָּרָ֔יו","חֶ֙רֶב֙","וְאָכְלָ֥ה","וְשָׂ֣בְעָ֔ה","וְרָוְתָ֖ה","מִדָּמָ֑ם","כִּ֣י","זֶ֠בַח","לַאדֹנָ֨י","יְהוִ֧ה","צְבָא֛וֹת","בְּאֶ֥רֶץ","צָפ֖וֹן","אֶל־","נְהַר־","פְּרָֽת׃"]},{"reference":"Jeremiah 50:15","eng_before":["Raise a war cry","against","her on every side!","She has thrown up","her hands in surrender;","her towers","have fallen;","her walls","are torn down.","Since","this","is the vengeance","of the LORD,"],"eng_word":"take out your vengeance upon her;","eng_after":["as","she has done,","do the same","to her."],"og_before":["הָרִ֨יעוּ","עָלֶ֤יהָ","סָבִיב֙","נָתְנָ֣ה","יָדָ֔הּ","אָשְׁיוֹתֶ֔יהָ","נָֽפְלוּ֙","חֽוֹמוֹתֶ֑יהָ","נֶהֶרְס֖וּ","כִּי֩","הִיא֙","נִקְמַ֨ת","יְהוָ֥ה"],"og_word":"הִנָּ֣קְמוּ","og_after":["כַּאֲשֶׁ֥ר","עָשְׂתָ֖ה","עֲשׂוּ־","לָֽהּ׃"]},{"reference":"Jeremiah 51:36","eng_before":["Therefore,","this is what","the LORD","says:","“Behold,","I will plead","your case"],"eng_word":"and take vengeance","eng_after":["on your behalf;","I will dry up","her sea","and make her springs","run dry."],"og_before":["לָכֵ֗ן","כֹּ֚ה","יְהוָ֔ה","אָמַ֣ר","הִנְנִי־","רָב֙","רִיבֵ֔ךְ"],"og_word":"וְנִקַּמְתִּ֖י","og_after":["נִקְמָתֵ֑ךְ","וְהַחֲרַבְתִּי֙","יַמָּ֔הּ","מְקוֹרָֽהּ׃","וְהֹבַשְׁתִּ֖י"]},{"reference":"Ezekiel 24:8","eng_before":["In order to stir up","wrath"],"eng_word":"and take vengeance,","eng_after":["I have placed","her blood","on","the bare","rock,","so that it would not","be covered.’"],"og_before":["לְהַעֲל֤וֹת","חֵמָה֙"],"og_word":"לִנְקֹ֣ם","og_after":["נָתַ֥תִּי","דָּמָ֖הּ","עַל־","צְחִ֣יחַ","סָ֑לַע","לְבִלְתִּ֖י","הִכָּסֽוֹת׃"]},{"reference":"Ezekiel 25:12","eng_before":["This is what","the Lord","GOD","says:","‘Because","Edom","acted"],"eng_word":"and in [so doing]","eng_after":["against the house","of Judah","incurred grievous guilt,"],"og_before":["כֹּ֤ה","אֲדֹנָ֣י","יְהוִ֔ה","אָמַר֙","יַ֣עַן","אֱד֛וֹם","עֲשׂ֥וֹת"],"og_word":"וְנִקְּמ֥וּ","og_after":["לְבֵ֣ית","יְהוּדָ֑ה","וַיֶּאְשְׁמ֥וּ"]},{"reference":"Ezekiel 25:12","eng_before":["This is what","the Lord","GOD","says:","‘Because","Edom","acted","vengefully","against the house","of Judah","and in [so doing]","incurred grievous guilt,"],"eng_after":[],"og_before":["כֹּ֤ה","אֲדֹנָ֣י","יְהוִ֔ה","אָמַר֙","יַ֣עַן","אֱד֛וֹם","עֲשׂ֥וֹת","בִּנְקֹ֥ם","לְבֵ֣ית","יְהוּדָ֑ה","וְנִקְּמ֥וּ","וַיֶּאְשְׁמ֥וּ"],"og_after":[]},{"reference":"Ezekiel 25:15","eng_before":["This is what","the Lord","GOD","says:","‘Because","the Philistines","acted","in vengeance"],"eng_word":"and took revenge","eng_after":["with contempt","of heart,","to destroy [Judah]","with ancient","hostility,"],"og_before":["כֹּ֤ה","אֲדֹנָ֣י","יְהוִ֔ה","אָמַר֙","יַ֛עַן","פְּלִשְׁתִּ֖ים","עֲשׂ֥וֹת","בִּנְקָמָ֑ה"],"og_word":"וַיִּנָּקְמ֤וּ","og_after":["בִּשְׁאָ֣ט","בְּנֶ֔פֶשׁ","לְמַשְׁחִ֖ית","עוֹלָֽם׃","אֵיבַ֥ת"]},{"reference":"Nahum 1:2","eng_before":["The LORD","is a jealous"],"eng_word":"takes vengeance","eng_after":["God;","the LORD","and full of wrath.","The LORD","on His foes","and reserves [wrath]","for His enemies."],"og_before":["יְהוָ֔ה","קַנּ֤וֹא"],"og_word":"נֹקֵ֤ם","og_after":["אֵ֣ל","יְהוָ֖ה","וּבַ֣עַל","יְהוָה֙","לְצָרָ֔יו","וְנוֹטֵ֥ר","לְאֹיְבָֽיו׃"]},{"reference":"Nahum 1:2","eng_before":["The LORD","is a jealous","and avenging","God;","the LORD","is avenging","and full of wrath.","The LORD","takes vengeance","on His foes","and reserves [wrath]","for His enemies."],"eng_after":[],"og_before":["יְהוָ֔ה","קַנּ֤וֹא","וְנֹקֵם֙","אֵ֣ל","יְהוָ֖ה","נֹקֵ֥ם","וּבַ֣עַל","יְהוָה֙","נֹקֵ֤ם","לְצָרָ֔יו","וְנוֹטֵ֥ר","לְאֹיְבָֽיו׃"],"og_after":[]},{"reference":"Nahum 1:2","eng_before":["The LORD","is a jealous","and avenging","God;","the LORD","is avenging","and full of wrath.","The LORD","takes vengeance","on His foes","and reserves [wrath]","for His enemies."],"eng_after":[],"og_before":["יְהוָ֔ה","קַנּ֤וֹא","וְנֹקֵם֙","אֵ֣ל","יְהוָ֖ה","נֹקֵ֥ם","וּבַ֣עַל","יְהוָה֙","נֹקֵ֤ם","לְצָרָ֔יו","וְנוֹטֵ֥ר","לְאֹיְבָֽיו׃"],"og_after":[]}]