[{"reference":"Leviticus 26:25","eng_before":["And I will bring","a sword","against you","to execute"],"eng_word":"the vengeance","eng_after":["of the covenant.","Though you withdraw","into","your cities,","I will send","a pestilence","among you,","and you will be delivered","into the hand","of the enemy."],"og_before":["וְהֵבֵאתִ֨י","חֶ֗רֶב","עֲלֵיכֶ֜ם","נֹקֶ֙מֶת֙"],"og_word":"נְקַם־","og_after":["בְּרִ֔ית","וְנֶאֱסַפְתֶּ֖ם","אֶל־","עָרֵיכֶ֑ם","וְשִׁלַּ֤חְתִּי","דֶ֙בֶר֙","בְּת֣וֹכְכֶ֔ם","וְנִתַּתֶּ֖ם","בְּיַד־","אוֹיֵֽב׃"]},{"reference":"Deuteronomy 32:35","eng_before":[],"eng_word":"Vengeance","eng_after":["is Mine;","I will repay.","In due time","their foot","will slip;","for","their day","of disaster","is near,","and their doom","is coming quickly."],"og_before":[],"og_word":"נָקָם֙","og_after":["לִ֤י","וְשִׁלֵּ֔ם","לְעֵ֖ת","רַגְלָ֑ם","תָּמ֣וּט","כִּ֤י","י֣וֹם","אֵידָ֔ם","קָרוֹב֙","עֲתִדֹ֥ת","וְחָ֖שׁ"]},{"reference":"Deuteronomy 32:41","eng_before":["when","I sharpen","My flashing","sword,","and My hand","grasps it","in judgment,","I will take"],"eng_word":"vengeance","eng_after":["on My adversaries","and repay","those who hate Me."],"og_before":["אִם־","שַׁנּוֹתִי֙","בְּרַ֣ק","חַרְבִּ֔י","יָדִ֑י","וְתֹאחֵ֥ז","בְּמִשְׁפָּ֖ט","אָשִׁ֤יב"],"og_word":"נָקָם֙","og_after":["לְצָרָ֔י","אֲשַׁלֵּֽם׃","וְלִמְשַׂנְאַ֖י"]},{"reference":"Deuteronomy 32:43","eng_before":["Rejoice, [O heavens, with Him, and let all God’s angels worship Him.]הַרְנִ֤ינוּ (har·nî·nū)Verb - Hifil - Imperative - masculine pluralStrong's 7442:  To give a ringing cry[Rejoice,] O Gentiles,גוֹיִם֙ (ḡō·w·yim)Noun - masculine pluralStrong's 1471:  A foreign nation, a Gentile, a troop of animals, a flight of locusts[with] His people;עַמּ֔וֹ (‘am·mōw)Noun - masculine singular construct | third person masculine singularStrong's 5971:  A people, a tribe, troops, attendants, a flockforכִּ֥י (kî)ConjunctionStrong's 3588:  A relative conjunctionHe will avengeיִקּ֑וֹם (yiq·qō·wm)Verb - Qal - Imperfect - third person masculine singularStrong's 5358:  To grudge, avenge, punishthe bloodדַם־ (ḏam-)Noun - masculine singular constructStrong's 1818:  Blood, of man, an animal, the juice of the grape, bloodshedof His children.עֲבָדָ֖יו (‘ă·ḇā·ḏāw)Noun - masculine plural construct | third person masculine singularStrong's 5650:  Slave, servantHe will takeיָשִׁ֣יב (yā·šîḇ)Verb - Hifil - Imperfect - third person masculine singularStrong's 7725:  To turn back, in, to retreat, againvengeanceוְנָקָם֙ (wə·nā·qām)Conjunctive waw | Noun - masculine singularStrong's 5359:  Vengeanceon His adversaries [and repay those who hate Him];לְצָרָ֔יו (lə·ṣā·rāw)Preposition-l | Noun - masculine plural construct | third person masculine singularStrong's 6862:  Narrow, a tight place, a pebble, an opponentHe will cleanseוְכִפֶּ֥ר (wə·ḵip·per)Conjunctive waw | Verb - Piel - Conjunctive perfect - third person masculine singularStrong's 3722:  To cover, to expiate, condone, to placate, cancelHis landאַדְמָת֖וֹ (’aḏ·mā·ṯōw)Noun - feminine singular construct | third person masculine singularStrong's 127:  Ground, land[and] His people.”עַמּֽוֹ׃ (‘am·mōw)Noun - masculine singular construct | third person masculine singularStrong's 5971:  A people, a tribe, troops, attendants, a flockJump to PreviousAdversaries Aloud Atone Avenge Avenges Avengeth Blood Enemies Expiation Haters Joy Makes Maketh Merciful Nations Pardoned Payment Praise Punishment Rejoice Render Rendereth Servants Shout Sin Sing Turneth VengeanceJump to NextAdversaries Aloud Atone Avenge Avenges Avengeth Blood Enemies Expiation Haters Joy Makes Maketh Merciful Nations Pardoned Payment Praise Punishment Rejoice Render Rendereth Servants Shout Sin Sing Turneth VengeanceLinksDeuteronomy 32:43 NIVDeuteronomy 32:43 NLTDeuteronomy 32:43 ESVDeuteronomy 32:43 NASBDeuteronomy 32:43 KJVDeuteronomy 32:43  BibleApps.comDeuteronomy 32:43 Biblia ParalelaDeuteronomy 32:43 Chinese BibleDeuteronomy 32:43 French BibleDeuteronomy 32:43 Clyx QuotationsOT Law: Deuteronomy 32:43 Rejoice you nations with his people (Deut. De Du)","[Rejoice,] O Gentiles,","[with] His people;","for","He will avenge","the blood","of His children.","He will take"],"eng_word":"vengeance","eng_after":["on His adversaries","He will cleanse","His land","[and] His people.”"],"og_before":["הַרְנִ֤ינוּ","גוֹיִם֙","עַמּ֔וֹ","כִּ֥י","יִקּ֑וֹם","דַם־","עֲבָדָ֖יו","יָשִׁ֣יב"],"og_word":"וְנָקָם֙","og_after":["לְצָרָ֔יו","וְכִפֶּ֥ר","אַדְמָת֖וֹ","עַמּֽוֹ׃"]},{"reference":"Judges 16:28","eng_before":["Then Samson","called out","to","the LORD:","“O Lord","GOD,","please","remember me.","Strengthen me,","O God,","just","once more,","so that with one"],"eng_word":"vengeful blow","eng_after":["I may pay back","the Philistines","for my two","eyes.”"],"og_before":["שִׁמְשׁ֛וֹן","וַיִּקְרָ֥א","אֶל־","יֱהֹוִ֡ה","אֲדֹנָ֣י","יְהוָ֖ה","נָא֩","זָכְרֵ֣נִי","וְחַזְּקֵ֨נִי","הָאֱלֹהִ֔ים","אַ֣ךְ","הַפַּ֤עַם","אַחַ֛ת"],"og_word":"נְקַם־","og_after":["וְאִנָּקְמָ֧ה","מִפְּלִשְׁתִּֽים׃","מִשְּׁתֵ֥י","עֵינַ֖י"]},{"reference":"Psalm 58:10","eng_before":["The righteous","will rejoice","when","they see"],"eng_word":"they are avenged;","eng_after":["they will wash","their feet","in the blood","of the wicked."],"og_before":["צַ֭דִּיק","יִשְׂמַ֣ח","כִּי־","חָזָ֣ה"],"og_word":"נָקָ֑ם","og_after":["יִ֝רְחַ֗ץ","פְּעָמָ֥יו","בְּדַ֣ם","הָרָשָֽׁע׃"]},{"reference":"Proverbs 6:34","eng_before":["For","jealousy","enrages a husband,","and he will show no","mercy","in the day"],"eng_word":"of vengeance.","eng_after":[],"og_before":["כִּֽי־","קִנְאָ֥ה","חֲמַת־","וְלֹֽא־","יַ֝חְמ֗וֹל","בְּי֣וֹם"],"og_word":"נָקָֽם׃","og_after":[]},{"reference":"Isaiah 34:8","eng_before":["For","the LORD","has a day"],"eng_word":"of vengeance,","eng_after":["a time","of retribution","for [Edom’s] hostility","against Zion."],"og_before":["כִּ֛י","לַֽיהוָ֑ה","י֥וֹם"],"og_word":"נָקָ֖ם","og_after":["שְׁנַ֥ת","שִׁלּוּמִ֖ים","לְרִ֥יב","צִיּֽוֹן׃"]},{"reference":"Isaiah 35:4","eng_before":["Say","to those with anxious","hearts:","“Be strong,","do not","fear!","Behold,","your God","will come"],"eng_word":"with vengeance.","eng_after":["With divine","retribution","He","will come","to save you.”"],"og_before":["אִמְרוּ֙","לְנִמְהֲרֵי־","לֵ֔ב","חִזְק֖וּ","אַל־","תִּירָ֑אוּ","הִנֵּ֤ה","אֱלֹֽהֵיכֶם֙","יָב֔וֹא"],"og_word":"נָקָ֣ם","og_after":["אֱלֹהִ֔ים","גְּמ֣וּל","ה֥וּא","יָב֖וֹא","וְיֹשַׁעֲכֶֽם׃"]},{"reference":"Isaiah 47:3","eng_before":["Your nakedness","will be uncovered","and","your shame","will be exposed.","I will take"],"eng_word":"vengeance;","eng_after":["I will spare","no","one."],"og_before":["עֶרְוָתֵ֔ךְ","תִּגָּל֙","גַּ֥ם","חֶרְפָּתֵ֑ךְ","תֵּרָאֶ֖ה","אֶקָּ֔ח"],"og_word":"נָקָ֣ם","og_after":["אֶפְגַּ֖ע","וְלֹ֥א","אָדָֽם׃"]},{"reference":"Isaiah 59:17","eng_before":["He put on","righteousness","like a breastplate,","and the helmet","of salvation","on His head;","He put on","garments"],"eng_word":"of vengeance","eng_after":["and wrapped Himself","in a cloak","of zeal."],"og_before":["וַיִּלְבַּ֤שׁ","צְדָקָה֙","כַּשִּׁרְיָ֔ן","וְכ֥וֹבַע","יְשׁוּעָ֖ה","בְּרֹאשׁ֑וֹ","וַיִּלְבַּ֞שׁ","בִּגְדֵ֤י"],"og_word":"נָקָם֙","og_after":["וַיַּ֥עַט","כַּמְעִ֖יל","קִנְאָֽה׃"]},{"reference":"Isaiah 61:2","eng_before":["to proclaim","the year","of the LORD’s","favor","and the day","of our God’s"],"eng_word":"vengeance,","eng_after":["to comfort","all","who mourn,"],"og_before":["לִקְרֹ֤א","שְׁנַת־","לַֽיהוָ֔ה","רָצוֹן֙","וְי֥וֹם","לֵאלֹהֵ֑ינוּ"],"og_word":"נָקָ֖ם","og_after":["לְנַחֵ֖ם","כָּל־","אֲבֵלִֽים׃"]},{"reference":"Isaiah 63:4","eng_before":["For","the day"],"eng_word":"of vengeance","eng_after":["was in My heart,","and the year","of My redemption","had come."],"og_before":["כִּ֛י","י֥וֹם"],"og_word":"נָקָ֖ם","og_after":["בְּלִבִּ֑י","וּשְׁנַ֥ת","גְּאוּלַ֖י","בָּֽאָה׃"]},{"reference":"Ezekiel 24:8","eng_before":["In order to stir up","wrath","and take vengeance,","I have placed","her blood","on","the bare","rock,","so that it would not","be covered.’"],"eng_after":[],"og_before":["לְהַעֲל֤וֹת","חֵמָה֙","לִנְקֹ֣ם","נָתַ֥תִּי","דָּמָ֖הּ","עַל־","צְחִ֣יחַ","סָ֑לַע","לְבִלְתִּ֖י","הִכָּסֽוֹת׃"],"og_after":[]},{"reference":"Ezekiel 25:12","eng_before":["This is what","the Lord","GOD","says:","‘Because","Edom","acted","vengefully","against the house","of Judah","and in [so doing]","incurred grievous guilt,"],"eng_after":[],"og_before":["כֹּ֤ה","אֲדֹנָ֣י","יְהוִ֔ה","אָמַר֙","יַ֣עַן","אֱד֛וֹם","עֲשׂ֥וֹת","בִּנְקֹ֥ם","לְבֵ֣ית","יְהוּדָ֑ה","וְנִקְּמ֥וּ","וַיֶּאְשְׁמ֥וּ"],"og_after":[]},{"reference":"Ezekiel 25:15","eng_before":["This is what","the Lord","GOD","says:","‘Because","the Philistines","acted","in vengeance","and took revenge","with contempt","of heart,","to destroy [Judah]","with ancient","hostility,"],"eng_after":[],"og_before":["כֹּ֤ה","אֲדֹנָ֣י","יְהוִ֔ה","אָמַר֙","יַ֛עַן","פְּלִשְׁתִּ֖ים","עֲשׂ֥וֹת","בִּנְקָמָ֑ה","וַיִּנָּקְמ֤וּ","בִּשְׁאָ֣ט","בְּנֶ֔פֶשׁ","לְמַשְׁחִ֖ית","עוֹלָֽם׃","אֵיבַ֥ת"],"og_after":[]},{"reference":"Micah 5:15","eng_before":["I will take"],"eng_word":"vengeance","eng_after":["in anger","and wrath","upon the nations","that","have not","obeyed Me.”"],"og_before":["וְעָשִׂ֜יתִי"],"og_word":"נָקָ֖ם","og_after":["בְּאַ֧ף","וּבְחֵמָ֛ה","הַגּוֹיִ֑ם","אֲשֶׁ֖ר","לֹ֥א","שָׁמֵֽעוּ׃"]}]