[
  {
    "word": "Your kingdom",
    "heb": "מַֽלְכוּתְךָ֗",
    "translit": "(mal·ḵū·ṯə·ḵā)",
    "parse": "Noun - feminine singular construct | second person masculine singular",
    "str": "Strong's 4438:  ",
    "str2": "Royalty, royal power, reign, kingdom"
  },
  {
    "word": "is an everlasting",
    "heb": "עֹֽלָמִ֑ים",
    "translit": "(‘ō·lā·mîm)",
    "parse": "Noun - masculine plural",
    "str": "Strong's 5769:  ",
    "str2": "Concealed, eternity, frequentatively, always"
  },
  {
    "word": "kingdom,",
    "heb": "מַלְכ֥וּת",
    "translit": "(mal·ḵūṯ)",
    "parse": "Noun - feminine singular construct",
    "str": "Strong's 4438:  ",
    "str2": "Royalty, royal power, reign, kingdom"
  },
  {
    "word": "and Your dominion",
    "heb": "וּ֝מֶֽמְשֶׁלְתְּךָ֗",
    "translit": "(ū·mem·šel·tə·ḵā)",
    "parse": "Conjunctive waw | Noun - feminine singular construct | second person masculine singular",
    "str": "Strong's 4475:  ",
    "str2": "Rule, a realm, a ruler"
  },
  {
    "word": "[endures] through",
    "heb": "בְּכָל־",
    "translit": "(bə·ḵāl)",
    "parse": "Preposition-b | Noun - masculine singular construct",
    "str": "Strong's 3605:  ",
    "str2": "The whole, all, any, every"
  },
  {
    "word": "all",
    "heb": "כָּל־",
    "translit": "(kāl-)",
    "parse": "Noun - masculine singular construct",
    "str": "Strong's 3605:  ",
    "str2": "The whole, all, any, every"
  },
  {
    "word": "generations.",
    "heb": "דּ֥וֹר",
    "translit": "(dō·wr)",
    "parse": "Noun - masculine singular",
    "str": "Strong's 1755:  ",
    "str2": "A revolution of time, an age, generation, a dwelling"
  },
  {
    "word": "The LORD is faithful in all His words and kind in all His actions.וָדֽוֹר׃ (wā·ḏō·wr)Conjunctive waw | Noun - masculine singularStrong's 1755:  A revolution of time, an age, generation, a dwellingJump to PreviousAges Deeds Dominion Endures Endureth Eternal Everlasting Faithful Generations Gracious Kingdom Loving Promises Rule Throughout WordsJump to NextAges Deeds Dominion Endures Endureth Eternal Everlasting Faithful Generations Gracious Kingdom Loving Promises Rule Throughout WordsLinksPsalm 145:13 NIVPsalm 145:13 NLTPsalm 145:13 ESVPsalm 145:13 NASBPsalm 145:13 KJVPsalm 145:13  BibleApps.comPsalm 145:13 Biblia ParalelaPsalm 145:13 Chinese BiblePsalm 145:13 French BiblePsalm 145:13 Clyx QuotationsOT Poetry: Psalm 145:13 Your kingdom is an everlasting kingdom (Psalm Ps Psa.) ",
    "heb": "וָדֽוֹר׃",
    "translit": "(wā·ḏō·wr)",
    "parse": "Conjunctive waw | Noun - masculine singular",
    "str": "Strong's 1755:  ",
    "str2": "A revolution of time, an age, generation, a dwelling"
  }
]