[
  {
    "word": "Rejoice, [O heavens, with Him, and let all God’s angels worship Him.]הַרְנִ֤ינוּ (har·nî·nū)Verb - Hifil - Imperative - masculine pluralStrong's 7442:  To give a ringing cry[Rejoice,] O Gentiles,גוֹיִם֙ (ḡō·w·yim)Noun - masculine pluralStrong's 1471:  A foreign nation, a Gentile, a troop of animals, a flight of locusts[with] His people;עַמּ֔וֹ (‘am·mōw)Noun - masculine singular construct | third person masculine singularStrong's 5971:  A people, a tribe, troops, attendants, a flockforכִּ֥י (kî)ConjunctionStrong's 3588:  A relative conjunctionHe will avengeיִקּ֑וֹם (yiq·qō·wm)Verb - Qal - Imperfect - third person masculine singularStrong's 5358:  To grudge, avenge, punishthe bloodדַם־ (ḏam-)Noun - masculine singular constructStrong's 1818:  Blood, of man, an animal, the juice of the grape, bloodshedof His children.עֲבָדָ֖יו (‘ă·ḇā·ḏāw)Noun - masculine plural construct | third person masculine singularStrong's 5650:  Slave, servantHe will takeיָשִׁ֣יב (yā·šîḇ)Verb - Hifil - Imperfect - third person masculine singularStrong's 7725:  To turn back, in, to retreat, againvengeanceוְנָקָם֙ (wə·nā·qām)Conjunctive waw | Noun - masculine singularStrong's 5359:  Vengeanceon His adversaries [and repay those who hate Him];לְצָרָ֔יו (lə·ṣā·rāw)Preposition-l | Noun - masculine plural construct | third person masculine singularStrong's 6862:  Narrow, a tight place, a pebble, an opponentHe will cleanseוְכִפֶּ֥ר (wə·ḵip·per)Conjunctive waw | Verb - Piel - Conjunctive perfect - third person masculine singularStrong's 3722:  To cover, to expiate, condone, to placate, cancelHis landאַדְמָת֖וֹ (’aḏ·mā·ṯōw)Noun - feminine singular construct | third person masculine singularStrong's 127:  Ground, land[and] His people.”עַמּֽוֹ׃ (‘am·mōw)Noun - masculine singular construct | third person masculine singularStrong's 5971:  A people, a tribe, troops, attendants, a flockJump to PreviousAdversaries Aloud Atone Avenge Avenges Avengeth Blood Enemies Expiation Haters Joy Makes Maketh Merciful Nations Pardoned Payment Praise Punishment Rejoice Render Rendereth Servants Shout Sin Sing Turneth VengeanceJump to NextAdversaries Aloud Atone Avenge Avenges Avengeth Blood Enemies Expiation Haters Joy Makes Maketh Merciful Nations Pardoned Payment Praise Punishment Rejoice Render Rendereth Servants Shout Sin Sing Turneth VengeanceLinksDeuteronomy 32:43 NIVDeuteronomy 32:43 NLTDeuteronomy 32:43 ESVDeuteronomy 32:43 NASBDeuteronomy 32:43 KJVDeuteronomy 32:43  BibleApps.comDeuteronomy 32:43 Biblia ParalelaDeuteronomy 32:43 Chinese BibleDeuteronomy 32:43 French BibleDeuteronomy 32:43 Clyx QuotationsOT Law: Deuteronomy 32:43 Rejoice you nations with his people (Deut. De Du)",
    "heb": "הַרְנִ֤ינוּ",
    "translit": "(har·nî·nū)",
    "parse": "Verb - Hifil - Imperative - masculine plural",
    "str": "Strong's 7442:  ",
    "str2": "To give a ringing cry"
  },
  {
    "word": "[Rejoice,] O Gentiles,",
    "heb": "גוֹיִם֙",
    "translit": "(ḡō·w·yim)",
    "parse": "Noun - masculine plural",
    "str": "Strong's 1471:  ",
    "str2": "A foreign nation, a Gentile, a troop of animals, a flight of locusts"
  },
  {
    "word": "[with] His people;",
    "heb": "עַמּ֔וֹ",
    "translit": "(‘am·mōw)",
    "parse": "Noun - masculine singular construct | third person masculine singular",
    "str": "Strong's 5971:  ",
    "str2": "A people, a tribe, troops, attendants, a flock"
  },
  {
    "word": "for",
    "heb": "כִּ֥י",
    "translit": "(kî)",
    "parse": "Conjunction",
    "str": "Strong's 3588:  ",
    "str2": "A relative conjunction"
  },
  {
    "word": "He will avenge",
    "heb": "יִקּ֑וֹם",
    "translit": "(yiq·qō·wm)",
    "parse": "Verb - Qal - Imperfect - third person masculine singular",
    "str": "Strong's 5358:  ",
    "str2": "To grudge, avenge, punish"
  },
  {
    "word": "the blood",
    "heb": "דַם־",
    "translit": "(ḏam-)",
    "parse": "Noun - masculine singular construct",
    "str": "Strong's 1818:  ",
    "str2": "Blood, of man, an animal, the juice of the grape, bloodshed"
  },
  {
    "word": "of His children.",
    "heb": "עֲבָדָ֖יו",
    "translit": "(‘ă·ḇā·ḏāw)",
    "parse": "Noun - masculine plural construct | third person masculine singular",
    "str": "Strong's 5650:  ",
    "str2": "Slave, servant"
  },
  {
    "word": "He will take",
    "heb": "יָשִׁ֣יב",
    "translit": "(yā·šîḇ)",
    "parse": "Verb - Hifil - Imperfect - third person masculine singular",
    "str": "Strong's 7725:  ",
    "str2": "To turn back, in, to retreat, again"
  },
  {
    "word": "vengeance",
    "heb": "וְנָקָם֙",
    "translit": "(wə·nā·qām)",
    "parse": "Conjunctive waw | Noun - masculine singular",
    "str": "Strong's 5359:  ",
    "str2": "Vengeance"
  },
  {
    "word": "on His adversaries",
    "heb": "לְצָרָ֔יו",
    "translit": "(lə·ṣā·rāw)",
    "parse": "Preposition-l | Noun - masculine plural construct | third person masculine singular",
    "str": "Strong's 6862:  ",
    "str2": "Narrow, a tight place, a pebble, an opponent"
  },
  {
    "word": "He will cleanse",
    "heb": "וְכִפֶּ֥ר",
    "translit": "(wə·ḵip·per)",
    "parse": "Conjunctive waw | Verb - Piel - Conjunctive perfect - third person masculine singular",
    "str": "Strong's 3722:  ",
    "str2": "To cover, to expiate, condone, to placate, cancel"
  },
  {
    "word": "His land",
    "heb": "אַדְמָת֖וֹ",
    "translit": "(’aḏ·mā·ṯōw)",
    "parse": "Noun - feminine singular construct | third person masculine singular",
    "str": "Strong's 127:  ",
    "str2": "Ground, land"
  },
  {
    "word": "[and] His people.”",
    "heb": "עַמּֽוֹ׃",
    "translit": "(‘am·mōw)",
    "parse": "Noun - masculine singular construct | third person masculine singular",
    "str": "Strong's 5971:  ",
    "str2": "A people, a tribe, troops, attendants, a flock"
  }
]